nozomipy/__init__.py
nozomipy/async_api.py
nozomipy/cmd.py
nozomipy/data.py
nozomipy/exceptions.py
nozomipy/helpers.py
nozomipy_async-1.0.0.dist-info/LICENSE
nozomipy_async-1.0.0.dist-info/METADATA
nozomipy_async-1.0.0.dist-info/WHEEL
nozomipy_async-1.0.0.dist-info/entry_points.txt
nozomipy_async-1.0.0.dist-info/top_level.txt
nozomipy_async-1.0.0.dist-info/RECORD
