Metadata-Version: 2.1
Name: nozomipy-async
Version: 1.0.0
Summary: Nozomi Async API for retrieving images, videos, gifs.
Home-page: https://github.com/Isotr0py/nozomipy-async
Author: Isotr0py
License: This is free and unencumbered software released into the public domain.        
Project-URL: Homepage, https://github.com/Isotr0py/nozomipy-async
Project-URL: Bug Tracker, https://github.com/Isotr0py/nozomipy-async/issues
Project-URL: Releases, https://github.com/Isotr0py/nozomipy-async/releases
Keywords: nozomi,nozomi.la,api,video,image,anime
Platform: UNKNOWN
Classifier: License :: OSI Approved :: MIT License
Classifier: Operating System :: OS Independent
Classifier: Programming Language :: Python :: 3.8
Classifier: Programming Language :: Python :: 3.9
Classifier: Programming Language :: Python :: 3.10
Requires-Python: >=3.8
License-File: LICENSE
Requires-Dist: aiohttp
Requires-Dist: dacite
